fiscal_calendar/__init__.py
fiscal_calendar/fiscal_calendar.py
fiscal_calendar/version.py
fiscal_calendar-0.2.17.dist-info/LICENSE
fiscal_calendar-0.2.17.dist-info/METADATA
fiscal_calendar-0.2.17.dist-info/WHEEL
fiscal_calendar-0.2.17.dist-info/top_level.txt
fiscal_calendar-0.2.17.dist-info/RECORD
