Metadata-Version: 2.1
Name: fiscal-calendar
Version: 0.2.17
Summary: Fiscal Retail Calendar - 4-5-4 week retail calendar
Home-page: https://github.com/tonyhollaar/fiscal_calendar
Download-URL: https://github.com/tonyhollaar/fiscal_calendar/archive/refs/tags/v0.2.tar.gz
Author: Tony Hollaar
Author-email: thollaar@gmail.com
License: MIT
Keywords: pypi,python,fiscal calendar,4-4-5 calendar,4-5-4 calendar,retail calendar,fiscal retail calendar,fiscal retail calendar generator,fiscal retail calendar generator python,fiscal retail calendar generator python package,fiscal retail calendar generator python package pypi,fiscal retail calendar generator python package pypi package,fiscal retail calendar generator python package pypi package 4-4-5,fiscal retail calendar generator python package pypi package 4-5-4,fiscal retail calendar g
Classifier: Development Status :: 4 - Beta
Classifier: Intended Audience :: Developers
Classifier: Topic :: Software Development :: Build Tools
Classifier: License :: OSI Approved :: MIT License
Classifier: Programming Language :: Python :: 3.7
Classifier: Programming Language :: Python :: 3.8
Classifier: Programming Language :: Python :: 3.9
Classifier: Programming Language :: Python :: 3.10
License-File: LICENSE
Requires-Dist: pandas >=1.0.0
Requires-Dist: numpy >=1.18.0
Requires-Dist: reportlab >=3.5.0
